pyxsb/__init__.py
py_xsb-1.0.0.dist-info/top_level.txt
py_xsb-1.0.0.dist-info/METADATA
py_xsb-1.0.0.dist-info/DESCRIPTION.rst
py_xsb-1.0.0.dist-info/metadata.json
py_xsb-1.0.0.dist-info/WHEEL
py_xsb-1.0.0.dist-info/RECORD
