Metadata-Version: 2.0
Name: py-xsb
Version: 1.0.0
Summary: Python interface for XSB
Home-page: https://github.com/gooofy/py-xsb
Author: Guenter Bartsch
Author-email: guenter@zamia.org
License: Apache
Keywords: XSB interface AI artificial intelligence reasoning programming in logic
Platform: Linux
Classifier: Topic :: Scientific/Engineering :: Artificial Intelligence
Classifier: Topic :: Software Development :: Libraries :: Python Modules
Classifier: Operating System :: POSIX :: Linux
Classifier: Operating System :: Microsoft :: Windows
Classifier: Operating System :: MacOS :: MacOS X
Classifier: License :: OSI Approved :: Apache Software License
Classifier: Programming Language :: Python :: 2
Classifier: Programming Language :: Python :: 2.7
Classifier: Programming Language :: Python :: 3
Classifier: Programming Language :: Python :: 3.6
Classifier: Programming Language :: Prolog
Classifier: Intended Audience :: Developers
Classifier: Intended Audience :: Science/Research
